qmxgraph/__init__.py
qmxgraph/_cherrypy_server.py
qmxgraph/_web_view.py
qmxgraph/api.py
qmxgraph/configuration.py
qmxgraph/constants.py
qmxgraph/debug.py
qmxgraph/deploy.py
qmxgraph/js.py
qmxgraph/mime.py
qmxgraph/render.py
qmxgraph/resource_mxgraph.py
qmxgraph/resource_qmxgraph.py
qmxgraph/server.py
qmxgraph/widget.py
qmxgraph-0.1.0.dist-info/DESCRIPTION.rst
qmxgraph-0.1.0.dist-info/METADATA
qmxgraph-0.1.0.dist-info/RECORD
qmxgraph-0.1.0.dist-info/WHEEL
qmxgraph-0.1.0.dist-info/metadata.json
qmxgraph-0.1.0.dist-info/top_level.txt
