Metadata-Version: 2.0
Name: qmxgraph
Version: 0.1.0
Summary: A Qt graph drawing widget using JavaScript's mxGraph library.
Home-page: https://github.com/ESSS/qmxgraph
Author: Rafael Bertoldi
Author-email: tochaman@gmail.com
License: MIT license
Keywords: qmxgraph
Platform: UNKNOWN
Classifier: Development Status :: 4 - Beta
Classifier: Intended Audience :: Developers
Classifier: License :: OSI Approved :: MIT License
Classifier: Natural Language :: English
Classifier: Operating System :: OS Independent
Classifier: Programming Language :: Python :: 3.5
Classifier: Programming Language :: Python :: 3.6
Classifier: Topic :: Scientific/Engineering :: Visualization
Classifier: Topic :: Software Development :: User Interfaces
